[
  { "titulo": "The Shawshank Redemption", "ano": "1994", "nota": "9.3" },
  { "titulo": "The Godfather", "ano": "1972", "nota": "9.3" },
  { "titulo": "The Dark Knight", "ano": "2008", "nota": "9.3" },
  { "titulo": "The Godfather Part II", "ano": "1974", "nota": "9.3" },
  { "titulo": "12 Angry Men", "ano": "1957", "nota": "9.3" },
  { "titulo": "Schindler's List", "ano": "1993", "nota": "9.3" },
  {
    "titulo": "The Lord of the Rings: The Return of the King",
    "ano": "2003",
    "nota": "9.3"
  },
  { "titulo": "Pulp Fiction", "ano": "1994", "nota": "9.3" },
  {
    "titulo": "The Lord of the Rings: The Fellowship of the Ring",
    "ano": "2001",
    "nota": "9.3"
  },
  {
    "titulo": ". The Good, the Bad and the Ugly",
    "ano": "1966",
    "nota": "9.3"
  },
  { "titulo": ". Forrest Gump", "ano": "1994", "nota": "9.3" },
  { "titulo": ". Fight Club", "ano": "1999", "nota": "9.3" },
  {
    "titulo": ". The Lord of the Rings: The Two Towers",
    "ano": "2002",
    "nota": "9.3"
  },
  { "titulo": ". Inception", "ano": "2010", "nota": "9.3" },
  {
    "titulo": ". Star Wars: Episode V - The Empire Strikes Back",
    "ano": "1980",
    "nota": "9.3"
  },
  { "titulo": ". The Matrix", "ano": "1999", "nota": "9.3" },
  { "titulo": ". Goodfellas", "ano": "1990", "nota": "9.3" },
  {
    "titulo": ". One Flew Over the Cuckoo's Nest",
    "ano": "1975",
    "nota": "9.3"
  },
  { "titulo": ". Se7en", "ano": "1995", "nota": "9.3" },
  { "titulo": ". It's a Wonderful Life", "ano": "1946", "nota": "9.3" },
  { "titulo": ". Seven Samurai", "ano": "1954", "nota": "9.3" },
  { "titulo": ". Interstellar", "ano": "2014", "nota": "9.3" },
  { "titulo": ". The Silence of the Lambs", "ano": "1991", "nota": "9.3" },
  { "titulo": ". Saving Private Ryan", "ano": "1998", "nota": "9.3" },
  { "titulo": ". City of God", "ano": "2002", "nota": "9.3" },
  { "titulo": ". Life Is Beautiful", "ano": "1997", "nota": "9.3" },
  { "titulo": ". The Green Mile", "ano": "1999", "nota": "9.3" },
  {
    "titulo": ". Star Wars: Episode IV - A New Hope",
    "ano": "1977",
    "nota": "9.3"
  },
  {
    "titulo": ". Spider-Man: Across the Spider-Verse",
    "ano": "2023",
    "nota": "9.3"
  },
  { "titulo": ". Terminator 2: Judgment Day", "ano": "1991", "nota": "9.3" },
  { "titulo": ". Back to the Future", "ano": "1985", "nota": "9.3" },
  { "titulo": ". Spirited Away", "ano": "2001", "nota": "9.3" },
  { "titulo": ". The Pianist", "ano": "2002", "nota": "9.3" },
  { "titulo": ". Parasite", "ano": "2019", "nota": "9.3" },
  { "titulo": ". Psycho", "ano": "1960", "nota": "9.3" },
  { "titulo": ". Gladiator", "ano": "2000", "nota": "9.3" },
  { "titulo": ". The Lion King", "ano": "1994", "nota": "9.3" },
  { "titulo": ". L\u00e9on: The Professional", "ano": "1994", "nota": "9.3" },
  { "titulo": ". American History X", "ano": "1998", "nota": "9.3" },
  { "titulo": ". The Departed", "ano": "2006", "nota": "9.3" },
  { "titulo": ". Whiplash", "ano": "2014", "nota": "9.3" },
  { "titulo": ". The Prestige", "ano": "2006", "nota": "9.3" },
  { "titulo": ". Grave of the Fireflies", "ano": "1988", "nota": "9.3" },
  { "titulo": ". The Usual Suspects", "ano": "1995", "nota": "9.3" },
  { "titulo": ". Harakiri", "ano": "1962", "nota": "9.3" },
  { "titulo": ". Casablanca", "ano": "1942", "nota": "9.3" },
  { "titulo": ". The Intouchables", "ano": "2011", "nota": "9.3" },
  { "titulo": ". Modern Times", "ano": "1936", "nota": "9.3" },
  { "titulo": ". Cinema Paradiso", "ano": "1988", "nota": "9.3" },
  { "titulo": ". Rear Window", "ano": "1954", "nota": "9.3" },
  { "titulo": ". Once Upon a Time in the West", "ano": "1968", "nota": "9.3" },
  { "titulo": ". Alien", "ano": "1979", "nota": "9.3" },
  { "titulo": ". City Lights", "ano": "1931", "nota": "9.3" },
  { "titulo": ". Apocalypse Now", "ano": "1979", "nota": "9.3" },
  { "titulo": ". Django Unchained", "ano": "2012", "nota": "9.3" },
  { "titulo": ". Memento", "ano": "2000", "nota": "9.3" },
  { "titulo": ". Raiders of the Lost Ark", "ano": "1981", "nota": "9.3" },
  { "titulo": ". WALL\u00b7E", "ano": "2008", "nota": "9.3" },
  { "titulo": ". The Lives of Others", "ano": "2006", "nota": "9.3" },
  { "titulo": ". Sunset Blvd.", "ano": "1950", "nota": "9.3" },
  { "titulo": ". Paths of Glory", "ano": "1957", "nota": "9.3" },
  { "titulo": ". Avengers: Infinity War", "ano": "2018", "nota": "9.3" },
  { "titulo": ". The Shining", "ano": "1980", "nota": "9.3" },
  {
    "titulo": ". Spider-Man: Into the Spider-Verse",
    "ano": "2018",
    "nota": "9.3"
  },
  { "titulo": ". Witness for the Prosecution", "ano": "1957", "nota": "9.3" },
  { "titulo": ". The Great Dictator", "ano": "1940", "nota": "9.3" },
  { "titulo": ". Aliens", "ano": "1986", "nota": "9.3" },
  { "titulo": "8. Oppenheimer", "ano": "2023", "nota": "9.3" },
  { "titulo": ". Inglourious Basterds", "ano": "2009", "nota": "9.3" },
  { "titulo": ". The Dark Knight Rises", "ano": "2012", "nota": "9.3" },
  { "titulo": ". American Beauty", "ano": "1999", "nota": "9.3" },
  {
    "titulo": ". Dr. Strangelove or: How I Learned to Stop Worrying and Love the Bomb",
    "ano": "1964",
    "nota": "9.3"
  },
  { "titulo": ". Oldboy", "ano": "2003", "nota": "9.3" },
  { "titulo": ". Coco", "ano": "2017", "nota": "9.3" },
  { "titulo": ". Amadeus", "ano": "1984", "nota": "9.3" },
  { "titulo": ". Toy Story", "ano": "1995", "nota": "9.3" },
  { "titulo": ". Das Boot", "ano": "1981", "nota": "9.3" },
  { "titulo": ". Braveheart", "ano": "1995", "nota": "9.3" },
  { "titulo": ". Avengers: Endgame", "ano": "2019", "nota": "9.3" },
  { "titulo": ". Joker", "ano": "2019", "nota": "9.3" },
  { "titulo": ". Princess Mononoke", "ano": "1997", "nota": "9.3" },
  { "titulo": ". Good Will Hunting", "ano": "1997", "nota": "9.3" },
  { "titulo": ". Your Name.", "ano": "2016", "nota": "9.3" },
  { "titulo": ". Once Upon a Time in America", "ano": "1984", "nota": "9.3" },
  { "titulo": ". 3 Idiots", "ano": "2009", "nota": "9.3" },
  { "titulo": ". High and Low", "ano": "1963", "nota": "9.3" },
  { "titulo": ". Singin' in the Rain", "ano": "1952", "nota": "9.3" },
  { "titulo": ". Capernaum", "ano": "2018", "nota": "9.3" },
  { "titulo": ". Requiem for a Dream", "ano": "2000", "nota": "9.3" },
  { "titulo": ". Come and See", "ano": "1985", "nota": "9.3" },
  { "titulo": ". Toy Story 3", "ano": "2010", "nota": "9.3" },
  {
    "titulo": ". Star Wars: Episode VI - Return of the Jedi",
    "ano": "1983",
    "nota": "9.3"
  },
  {
    "titulo": ". Eternal Sunshine of the Spotless Mind",
    "ano": "2004",
    "nota": "9.3"
  },
  { "titulo": ". The Hunt", "ano": "2012", "nota": "9.3" },
  { "titulo": ". 2001: A Space Odyssey", "ano": "1968", "nota": "9.3" },
  { "titulo": ". Reservoir Dogs", "ano": "1992", "nota": "9.3" },
  { "titulo": ". Ikiru", "ano": "1952", "nota": "9.3" },
  { "titulo": ". Lawrence of Arabia", "ano": "1962", "nota": "9.3" },
  { "titulo": ". The Apartment", "ano": "1960", "nota": "9.3" },
  { "titulo": "00. Citizen Kane", "ano": "1941", "nota": "9.3" },
  { "titulo": "01. M", "ano": "1931", "nota": "9.3" },
  { "titulo": "02. North by Northwest", "ano": "1959", "nota": "9.3" },
  { "titulo": "03. Vertigo", "ano": "1958", "nota": "9.3" },
  { "titulo": "04. Double Indemnity", "ano": "1944", "nota": "9.3" },
  { "titulo": "05. Scarface", "ano": "1983", "nota": "9.3" },
  { "titulo": "06. Am\u00e9lie", "ano": "2001", "nota": "9.3" },
  { "titulo": "07. Full Metal Jacket", "ano": "1987", "nota": "9.3" },
  { "titulo": "08. Incendies", "ano": "2010", "nota": "9.3" },
  { "titulo": "09. A Clockwork Orange", "ano": "1971", "nota": "9.3" },
  { "titulo": "10. Heat", "ano": "1995", "nota": "9.3" },
  { "titulo": "11. Up", "ano": "2009", "nota": "9.3" },
  { "titulo": "12. To Kill a Mockingbird", "ano": "1962", "nota": "9.3" },
  { "titulo": "13. The Sting", "ano": "1973", "nota": "9.3" },
  { "titulo": "14. A Separation", "ano": "2011", "nota": "9.3" },
  { "titulo": "15. Hamilton", "ano": "2020", "nota": "9.3" },
  {
    "titulo": "16. Indiana Jones and the Last Crusade",
    "ano": "1989",
    "nota": "9.3"
  },
  { "titulo": "17. Die Hard", "ano": "1988", "nota": "9.3" },
  { "titulo": "18. Metropolis", "ano": "1927", "nota": "9.3" },
  { "titulo": "19. Like Stars on Earth", "ano": "2007", "nota": "9.3" },
  { "titulo": "20. Snatch", "ano": "2000", "nota": "9.3" },
  { "titulo": "21. Bicycle Thieves", "ano": "1948", "nota": "9.3" },
  { "titulo": "22. L.A. Confidential", "ano": "1997", "nota": "9.3" },
  { "titulo": "23. 1917", "ano": "2019", "nota": "9.3" },
  { "titulo": "24. Taxi Driver", "ano": "1976", "nota": "9.3" },
  { "titulo": "25. Downfall", "ano": "2004", "nota": "9.3" },
  { "titulo": "26. Dangal", "ano": "2016", "nota": "9.3" },
  { "titulo": "27. For a Few Dollars More", "ano": "1965", "nota": "9.3" },
  { "titulo": "28. Batman Begins", "ano": "2005", "nota": "9.3" },
  { "titulo": "29. Some Like It Hot", "ano": "1959", "nota": "9.3" },
  { "titulo": "30. Top Gun: Maverick", "ano": "2022", "nota": "9.3" },
  { "titulo": "31. The Wolf of Wall Street", "ano": "2013", "nota": "9.3" },
  { "titulo": "32. The Kid", "ano": "1921", "nota": "9.3" },
  { "titulo": "133. The Father", "ano": "2020", "nota": "9.3" },
  { "titulo": "34. Green Book", "ano": "2018", "nota": "9.3" },
  { "titulo": "35. All About Eve", "ano": "1950", "nota": "9.3" },
  { "titulo": "36. Judgment at Nuremberg", "ano": "1961", "nota": "9.3" },
  { "titulo": "37. The Truman Show", "ano": "1998", "nota": "9.3" },
  { "titulo": "38. There Will Be Blood", "ano": "2007", "nota": "9.3" },
  { "titulo": "39. Casino", "ano": "1995", "nota": "9.3" },
  { "titulo": "40. Shutter Island", "ano": "2010", "nota": "9.3" },
  { "titulo": "41. Ran", "ano": "1985", "nota": "9.3" },
  { "titulo": "42. Jurassic Park", "ano": "1993", "nota": "9.3" },
  { "titulo": "43. Pan's Labyrinth", "ano": "2006", "nota": "9.3" },
  { "titulo": "44. The Sixth Sense", "ano": "1999", "nota": "9.3" },
  { "titulo": "45. Unforgiven", "ano": "1992", "nota": "9.3" },
  { "titulo": "46. A Beautiful Mind", "ano": "2001", "nota": "9.3" },
  { "titulo": "47. No Country for Old Men", "ano": "2007", "nota": "9.3" },
  {
    "titulo": "48. The Treasure of the Sierra Madre",
    "ano": "1948",
    "nota": "9.3"
  },
  { "titulo": "49. Yojimbo", "ano": "1961", "nota": "9.3" },
  { "titulo": "50. The Thing", "ano": "1982", "nota": "9.3" },
  { "titulo": "51. Kill Bill: Vol. 1", "ano": "2003", "nota": "9.3" },
  {
    "titulo": "52. Monty Python and the Holy Grail",
    "ano": "1975",
    "nota": "9.3"
  },
  { "titulo": "53. The Great Escape", "ano": "1963", "nota": "9.3" },
  { "titulo": "54. Finding Nemo", "ano": "2003", "nota": "9.3" },
  { "titulo": "55. Rashomon", "ano": "1950", "nota": "9.3" },
  { "titulo": "56. The Elephant Man", "ano": "1980", "nota": "9.3" },
  { "titulo": "57. Chinatown", "ano": "1974", "nota": "9.3" },
  { "titulo": "58. Howl's Moving Castle", "ano": "2004", "nota": "9.3" },
  { "titulo": "59. Dial M for Murder", "ano": "1954", "nota": "9.3" },
  { "titulo": "60. Prisoners", "ano": "2013", "nota": "9.3" },
  { "titulo": "61. Gone with the Wind", "ano": "1939", "nota": "9.3" },
  { "titulo": "62. V for Vendetta", "ano": "2005", "nota": "9.3" },
  { "titulo": "63. Raging Bull", "ano": "1980", "nota": "9.3" },
  {
    "titulo": "64. Lock, Stock and Two Smoking Barrels",
    "ano": "1998",
    "nota": "9.3"
  },
  { "titulo": "65. The Secret in Their Eyes", "ano": "2009", "nota": "9.3" },
  { "titulo": "66. Inside Out", "ano": "2015", "nota": "9.3" },
  {
    "titulo": "67. Three Billboards Outside Ebbing, Missouri",
    "ano": "2017",
    "nota": "9.3"
  },
  { "titulo": "168. Spider-Man: No Way Home", "ano": "2021", "nota": "9.3" },
  { "titulo": "69. Trainspotting", "ano": "1996", "nota": "9.3" },
  {
    "titulo": "70. The Bridge on the River Kwai",
    "ano": "1957",
    "nota": "9.3"
  },
  { "titulo": "71. Fargo", "ano": "1996", "nota": "9.3" },
  { "titulo": "72. Warrior", "ano": "2011", "nota": "9.3" },
  { "titulo": "73. Catch Me If You Can", "ano": "2002", "nota": "9.3" },
  { "titulo": "74. Gran Torino", "ano": "2008", "nota": "9.3" },
  { "titulo": "75. Klaus", "ano": "2019", "nota": "9.3" },
  { "titulo": "176. Godzilla Minus One", "ano": "2023", "nota": "9.3" },
  { "titulo": "77. My Neighbor Totoro", "ano": "1988", "nota": "9.3" },
  { "titulo": "78. Million Dollar Baby", "ano": "2004", "nota": "9.3" },
  {
    "titulo": "79. Harry Potter and the Deathly Hallows: Part 2",
    "ano": "2011",
    "nota": "9.3"
  },
  { "titulo": "80. Children of Heaven", "ano": "1997", "nota": "9.3" },
  { "titulo": "81. Blade Runner", "ano": "1982", "nota": "9.3" },
  { "titulo": "82. 12 Years a Slave", "ano": "2013", "nota": "9.3" },
  { "titulo": "83. Before Sunrise", "ano": "1995", "nota": "9.3" },
  { "titulo": "84. The Grand Budapest Hotel", "ano": "2014", "nota": "9.3" },
  { "titulo": "85. Ben-Hur", "ano": "1959", "nota": "9.3" },
  { "titulo": "86. Barry Lyndon", "ano": "1975", "nota": "9.3" },
  { "titulo": "87. Gone Girl", "ano": "2014", "nota": "9.3" },
  { "titulo": "88. The Gold Rush", "ano": "1925", "nota": "9.3" },
  { "titulo": "89. Hacksaw Ridge", "ano": "2016", "nota": "9.3" },
  { "titulo": "90. In the Name of the Father", "ano": "1993", "nota": "9.3" },
  { "titulo": "91. Memories of Murder", "ano": "2003", "nota": "9.3" },
  { "titulo": "92. On the Waterfront", "ano": "1954", "nota": "9.3" },
  { "titulo": "93. The General", "ano": "1926", "nota": "9.3" },
  { "titulo": "94. The Deer Hunter", "ano": "1978", "nota": "9.3" },
  { "titulo": "95. Wild Tales", "ano": "2014", "nota": "9.3" },
  { "titulo": "96. Dead Poets Society", "ano": "1989", "nota": "9.3" },
  { "titulo": "97. Wild Strawberries", "ano": "1957", "nota": "9.3" },
  { "titulo": "98. Mad Max: Fury Road", "ano": "2015", "nota": "9.3" },
  { "titulo": "99. The Third Man", "ano": "1949", "nota": "9.3" },
  { "titulo": "00. The Wages of Fear", "ano": "1953", "nota": "9.3" },
  { "titulo": "01. Sherlock Jr.", "ano": "1924", "nota": "9.3" },
  { "titulo": "02. Monsters, Inc.", "ano": "2001", "nota": "9.3" },
  { "titulo": "03. Jaws", "ano": "1975", "nota": "9.3" },
  {
    "titulo": "04. Mr. Smith Goes to Washington",
    "ano": "1939",
    "nota": "9.3"
  },
  { "titulo": "05. How to Train Your Dragon", "ano": "2010", "nota": "9.3" },
  { "titulo": "06. Mary and Max", "ano": "2009", "nota": "9.3" },
  { "titulo": "07. Ford v Ferrari", "ano": "2019", "nota": "9.3" },
  { "titulo": "08. The Seventh Seal", "ano": "1957", "nota": "9.3" },
  { "titulo": "09. Ratatouille", "ano": "2007", "nota": "9.3" },
  { "titulo": "10. Room", "ano": "2015", "nota": "9.3" },
  { "titulo": "11. The Big Lebowski", "ano": "1998", "nota": "9.3" },
  { "titulo": "12. Tokyo Story", "ano": "1953", "nota": "9.3" },
  { "titulo": "13. Rocky", "ano": "1976", "nota": "9.3" },
  { "titulo": "14. Hotel Rwanda", "ano": "2004", "nota": "9.3" },
  { "titulo": "15. Logan", "ano": "2017", "nota": "9.3" },
  { "titulo": "16. Spotlight", "ano": "2015", "nota": "9.3" },
  { "titulo": "17. Platoon", "ano": "1986", "nota": "9.3" },
  { "titulo": "18. The Passion of Joan of Arc", "ano": "1928", "nota": "9.3" },
  { "titulo": "19. The Terminator", "ano": "1984", "nota": "9.3" },
  { "titulo": "220. Jai Bhim", "ano": "2021", "nota": "9.3" },
  { "titulo": "21. Before Sunset", "ano": "2004", "nota": "9.3" },
  { "titulo": "22. Rush", "ano": "2013", "nota": "9.3" },
  { "titulo": "23. Network", "ano": "1976", "nota": "9.3" },
  { "titulo": "24. The Best Years of Our Lives", "ano": "1946", "nota": "9.3" },
  { "titulo": "25. The Exorcist", "ano": "1973", "nota": "9.3" },
  { "titulo": "26. Stand by Me", "ano": "1986", "nota": "9.3" },
  { "titulo": "27. La haine", "ano": "1995", "nota": "9.3" },
  {
    "titulo": "28. Pirates of the Caribbean: The Curse of the Black Pearl",
    "ano": "2003",
    "nota": "9.3"
  },
  { "titulo": "29. The Wizard of Oz", "ano": "1939", "nota": "9.3" },
  { "titulo": "30. The Incredibles", "ano": "2004", "nota": "9.3" },
  { "titulo": "31. Into the Wild", "ano": "2007", "nota": "9.3" },
  { "titulo": "32. Hachi: A Dog's Tale", "ano": "2009", "nota": "9.3" },
  { "titulo": "33. To Be or Not to Be", "ano": "1942", "nota": "9.3" },
  { "titulo": "34. The Handmaiden", "ano": "2016", "nota": "9.3" },
  { "titulo": "35. My Father and My Son", "ano": "2005", "nota": "9.3" },
  { "titulo": "36. The Battle of Algiers", "ano": "1966", "nota": "9.3" },
  { "titulo": "37. Groundhog Day", "ano": "1993", "nota": "9.3" },
  { "titulo": "38. The Grapes of Wrath", "ano": "1940", "nota": "9.3" },
  { "titulo": "39. The Sound of Music", "ano": "1965", "nota": "9.3" },
  { "titulo": "40. Amores Perros", "ano": "2000", "nota": "9.3" },
  { "titulo": "41. Rebecca", "ano": "1940", "nota": "9.3" },
  { "titulo": "42. Cool Hand Luke", "ano": "1967", "nota": "9.3" },
  { "titulo": "43. The Iron Giant", "ano": "1999", "nota": "9.3" },
  { "titulo": "44. The Help", "ano": "2011", "nota": "9.3" },
  { "titulo": "45. It Happened One Night", "ano": "1934", "nota": "9.3" },
  { "titulo": "46. Pather Panchali", "ano": "1955", "nota": "9.3" },
  { "titulo": "47. The 400 Blows", "ano": "1959", "nota": "9.3" },
  { "titulo": "48. Aladdin", "ano": "1992", "nota": "9.3" },
  { "titulo": "49. Dances with Wolves", "ano": "1990", "nota": "9.3" },
  { "titulo": "50. Drishyam", "ano": "2015", "nota": "9.3" }
]
